djambe/__init__.py
djambe/main.py
djambe-0.1.0.dist-info/METADATA
djambe-0.1.0.dist-info/WHEEL
djambe-0.1.0.dist-info/licenses/LICENSE
djambe-0.1.0.dist-info/RECORD
